x402_hpke/__init__.py
x402_hpke/aad.py
x402_hpke/constants.py
x402_hpke/envelope.py
x402_hpke/errors.py
x402_hpke/extensions.py
x402_hpke/headers.py
x402_hpke/helpers.py
x402_hpke/keys.py
x402_hpke/payment.py
x402_hpke/secure_transport.py
x402_hpke/streaming.py
x402_hpke-0.2.0a0.dist-info/METADATA
x402_hpke-0.2.0a0.dist-info/WHEEL
x402_hpke-0.2.0a0.dist-info/RECORD
