Metadata-Version: 2.1
Name: x402-hpke
Version: 0.2.0a0
Summary: Provider-agnostic HPKE envelope for the x402 spec. A utility for confidential, verifiable payment requests and receipts across untrusted intermediaries, using canonical AAD, optional sidecar projection, and cross-language (Python/Node) interoperability.
Home-page: https://scrypted.ai
License: MIT
Keywords: hpke,aead,x25519,jwks,envelope
Author: Tim Cotten
Author-email: tcotten@scrypted.ai
Requires-Python: >=3.12
Classifier: Development Status :: 3 - Alpha
Classifier: License :: OSI Approved :: MIT License
Classifier: Programming Language :: Python :: 3
Classifier: Programming Language :: Python :: 3.12
Classifier: Programming Language :: Python :: 3.13
Classifier: Topic :: Security :: Cryptography
Requires-Dist: PyNaCl (>=1.5.0,<2.0.0)
Requires-Dist: requests (>=2.32.3,<3.0.0)
Project-URL: Documentation, https://github.com/scryptedai/x402-hpke/tree/main/docs
Project-URL: Repository, https://github.com/scryptedai/x402-hpke
